c8yrc/__init__.py
c8yrc/main.py
c8yrc/proxy_thread.py
c8yrc/rest_client/__init__.py
c8yrc/rest_client/c8y_enterprise.py
c8yrc/rest_client/c8y_exception.py
c8yrc/rest_client/c8y_rest_client.py
c8yrc/rest_client/c8y_rest_client_test.py
c8yrc/rest_client/c8yclient.py
c8yrc/rest_client/rest_constants.py
c8yrc/tcp_socket/__init__.py
c8yrc/tcp_socket/tcp_server.py
c8yrc/websocket_client/__init__.py
c8yrc/websocket_client/ws_client.py
c8yrc-1.1.1.dist-info/LICENSE
c8yrc-1.1.1.dist-info/METADATA
c8yrc-1.1.1.dist-info/WHEEL
c8yrc-1.1.1.dist-info/entry_points.txt
c8yrc-1.1.1.dist-info/top_level.txt
c8yrc-1.1.1.dist-info/RECORD
