Metadata-Version: 2.1
Name: c8yrc
Version: 1.1.1
Summary: Cumulocity Rest Client
Home-page: UNKNOWN
License: Apache v2
Platform: UNKNOWN
License-File: LICENSE
Requires-Dist: requests (>=2.26.0)
Requires-Dist: requests-toolbelt (>=0.9.1)
Requires-Dist: websocket-client (>=1.2.1)
